gcn10py/__init__.py
gcn10py/cli.py
gcn10py/gcn10
gcn10py-0.1.1.dist-info/METADATA
gcn10py-0.1.1.dist-info/WHEEL
gcn10py-0.1.1.dist-info/entry_points.txt
gcn10py-0.1.1.dist-info/licenses/LICENSE
gcn10py-0.1.1.dist-info/RECORD
