Metadata-Version: 2.4
Name: gcn10py
Version: 0.1.1
Summary: Python interface to the high-performance, MPI-Parallelized C executable `gcn10` for generating high-resolution Global Curve Number 10m rasters
Project-URL: Homepage, https://github.com/mabdazzam/gcn10py
Project-URL: Repository, https://github.com/mabdazzam/gcn10py
Project-URL: Documentation, https://github.com/mabdazzam/gcn10py/wiki
Author-email: Abdullah Azzam <mabdazzam@outlook.com>
License:                     GNU GENERAL PUBLIC LICENSE
License-File: LICENSE
Keywords: curve-number,gcn10,geospatial,hydrology
Classifier: License :: OSI Approved :: GNU General Public License v3 (GPLv3)
Classifier: Operating System :: OS Independent
Classifier: Programming Language :: Python :: 3
Requires-Python: >=3.10
